{
  "$schema": "http://json-schema.org/draft-07/schema",
  "title": "MCP Data Extraction executor",
  "description": "Extract primitives data, examples, and reusable components for the MCP server",
  "type": "object",
  "properties": {
    "outputPath": {
      "type": "string",
      "description": "The path where the generated data files will be written",
      "default": "packages/mcp/src/generated"
    },
    "primitivesPath": {
      "type": "string",
      "description": "The path to the ng-primitives package",
      "default": "packages/ng-primitives"
    },
    "docsPath": {
      "type": "string",
      "description": "The path to the documentation app",
      "default": "apps/documentation/src/app/pages/(documentation)"
    },
    "componentsPath": {
      "type": "string",
      "description": "The path to the reusable components",
      "default": "apps/components/src/app/pages/reusable-components"
    }
  },
  "required": []
}
